{
  "jogos": [
    {
      "nome": "Darksiders 2",
      "imagem": "games/darksiders_2.jpg",
      "valor": "$ 60,00",
      "id": "7e82"
    },
    {
      "nome": "Darksouls",
      "imagem": "games/darksouls.jpg",
      "valor": "$ 60,00",
      "id": "c584"
    },
    {
      "nome": "Dead Space",
      "imagem": "games/Dead_Space_3.jpg",
      "valor": "$ 60,00",
      "id": "91ab"
    },
    {
      "nome": "Dishonored",
      "imagem": "games/Dishonored.jpg",
      "valor": "$ 60,00",
      "id": "5a03"
    },
    {
      "nome": "Far Cry 3",
      "imagem": "games/Far_Cry_3.jpg",
      "valor": "$ 60,00",
      "id": "c268"
    },
    {
      "nome": "GTA V",
      "imagem": "games/GTA-V.jpg",
      "valor": "$ 60,00",
      "id": "49cc"
    },
    {
      "nome": "Halo 4",
      "imagem": "games/halo4.jpg",
      "valor": "$ 60,00",
      "id": "8d19"
    },
    {
      "nome": "Resident Evil 5",
      "imagem": "games/resident-evil-5.webp",
      "valor": "$ 60,00",
      "id": "0c59"
    },
    {
      "nome": "Gears of War 3",
      "imagem": "games/Gears-of-War-3.jpg",
      "valor": "$ 60,00",
      "id": "a6d2"
    },
    {
      "nome": "Tomb Raider",
      "imagem": "games/tomb_raider.jpg",
      "valor": "$ 60,00",
      "id": "43dd"
    },
    {
      "id": "7b61",
      "nome": "maluco",
      "valor": "55",
      "imagem": "https://images.app.goo.gl/9yKE7Tm1BtcsMqAv9"
    },
    {
      "id": "59ea",
      "nome": "aa",
      "valor": "222",
      "imagem": "http://127.0.0.1:5501/games/Gears-of-War-3.jpg"
    },
    {
      "id": "115d",
      "nome": "youtube",
      "valor": "22,12",
      "imagem": "https://i.ytimg.com/vi/UpWEe7iPd14/sddefault.jpg"
    },
    {
      "id": "8956",
      "nome": "trabalho de bicheiro",
      "valor": "25,50",
      "imagem": "https://i.ytimg.com/vi/ZUSbljmkZd4/hq720.jpg?sqp=-…RUAAIhCGAE=&rs=AOn4CLBMCHhNFvssVG9QfEdqMafhlIQa7g"
    },
    {
      "id": "cc3a",
      "nome": "carpinteiro",
      "valor": "22,42",
      "imagem": "\thttps://i.ytimg.com/vi/PmDtOBtZzhQ/hq720.jpg?sqp=-…RUAAIhCGAE=&rs=AOn4CLCk1G09Wz47wXvHsDswtIa590lYCQ",
      "status": true
    },
    {
      "id": "ee69",
      "valor": "11",
      "imagem": "https://i.ytimg.com/vi/PmDtOBtZzhQ/hq720.jpg?sqp=-…RUAAIhCGAE=&rs=AOn4CLCk1G09Wz47wXvHsDswtIa590lYCQ",
      "status": true
    },
    {
      "id": "d913",
      "valor": "12,24",
      "imagem": "\thttps://i.ytimg.com/vi/tlHVd6NTLE0/hq720.jpg",
      "status": true
    },
    {
      "id": "3bc6",
      "valor": "aa",
      "imagem": "\thttps://i.ytimg.com/vi/tlHVd6NTLE0/hq720.jpg",
      "status": true
    },
    {
      "id": "97c0",
      "valor": "12",
      "imagem": "\thttps://i.ytimg.com/vi/tlHVd6NTLE0/hq720.jpg",
      "status": true
    },
    {
      "id": "ac20",
      "nome": "oi",
      "valor": "12",
      "imagem": "\thttps://i.ytimg.com/vi/tlHVd6NTLE0/hq720.jpg"
    },
    {
      "id": "f8b6",
      "nome": "joao",
      "valor": "31,55",
      "imagem": "https://i.ytimg.com/vi/3J1xBL7zJXg/hqdefault.jpg"
    }
  ]
}